pytest_markdown/__init__.py
pytest_markdown/plugin.py
pytest_markdown-1.0.2.dist-info/entry_points.txt
pytest_markdown-1.0.2.dist-info/WHEEL
pytest_markdown-1.0.2.dist-info/METADATA
pytest_markdown-1.0.2.dist-info/RECORD
